jupyter_server_user_token/__init__.py
jupyter_server_user_token-0.1.0.data/data/etc/jupyter/jupyter_server_config.d/jupyter_server_user_token.json
jupyter_server_user_token-0.1.0.dist-info/METADATA
jupyter_server_user_token-0.1.0.dist-info/WHEEL
jupyter_server_user_token-0.1.0.dist-info/licenses/LICENSE
jupyter_server_user_token-0.1.0.dist-info/RECORD
