Metadata-Version: 2.3
Name: jupyter-server-user-token
Version: 0.1.0
Summary: Jupyter Server Extension to inject the User Token into the Jupyter Server environment
Project-URL: Home, https://github.com/curvenote/jupyter-server-user-token
Author-email: Steve Purves <steve@curvenote.com>
License: Copyright 2024 Curvenote
License-File: LICENSE
Keywords: Auth,Extension,Jupyter
Classifier: Framework :: Jupyter
Classifier: License :: OSI Approved :: MIT License
Classifier: Programming Language :: Python
Classifier: Programming Language :: Python :: 3
Classifier: Programming Language :: Python :: 3.8
Classifier: Programming Language :: Python :: 3.9
Classifier: Programming Language :: Python :: 3.10
Classifier: Programming Language :: Python :: 3.11
Requires-Dist: jupyter-server
